MANIFEST.in
README.txt
setup.cfg
setup.py
csci/__init__.py
csci.fourthplinth.egg-info/PKG-INFO
csci.fourthplinth.egg-info/SOURCES.txt
csci.fourthplinth.egg-info/dependency_links.txt
csci.fourthplinth.egg-info/entry_points.txt
csci.fourthplinth.egg-info/namespace_packages.txt
csci.fourthplinth.egg-info/not-zip-safe
csci.fourthplinth.egg-info/paster_plugins.txt
csci.fourthplinth.egg-info/requires.txt
csci.fourthplinth.egg-info/top_level.txt
csci/fourthplinth/README.txt
csci/fourthplinth/__init__.py
csci/fourthplinth/config.py
csci/fourthplinth/configure.zcml
csci/fourthplinth/browser/__init__.py
csci/fourthplinth/browser/configure.zcml
csci/fourthplinth/browser/fpscheduleview.pt
csci/fourthplinth/browser/fpscheduleview.py
csci/fourthplinth/browser/google_short.py
csci/fourthplinth/browser/udscheduleview.pt
csci/fourthplinth/browser/udscheduleview.py
csci/fourthplinth/content/__init__.py
csci/fourthplinth/content/configure.zcml
csci/fourthplinth/content/fourthplinth.py
csci/fourthplinth/interfaces/__init__.py
csci/fourthplinth/interfaces/fourthplinth.py
csci/fourthplinth/portlets/__init__.py
csci/fourthplinth/portlets/configure.zcml
csci/fourthplinth/profiles/default/factorytool.xml
csci/fourthplinth/profiles/default/metadata.xml
csci/fourthplinth/profiles/default/portlets.xml
csci/fourthplinth/profiles/default/rolemap.xml
csci/fourthplinth/profiles/default/types.xml
csci/fourthplinth/profiles/default/types/fourthplinth.xml
csci/fourthplinth/tests/__init__.py
csci/fourthplinth/tests/base.py
csci/fourthplinth/tests/test_doctest.py