Metadata-Version: 1.0
Name: csci.fourthplinth
Version: 0.5dev
Summary: Post the fourthplinth schedule to twitter daily
Home-page: www.cannonscientific.com
Author: Peter Dyson
Author-email: pdyson@cannonscientific.com
License: GPL
Keywords: trafalgar square fourth plinth arts plone cannon scientific
Platform: UNKNOWN
Classifier: Framework :: Plone
Classifier: Intended Audience :: Developers
Classifier: Topic :: Software Development :: Libraries :: Python Modules
Classifier: License :: OSI Approved :: GNU General Public License (GPL)
